{
  "last_updated": "2025-08-21T12:19:43.776739",
  "clients": [
    {
      "id": "20250821_091739",
      "name": "GLADYS VILLA",
      "created_at": "2025-08-21T09:17:39.883093",
      "data": {
        "client_document_number": "1937582628",
        "client_first_name": "GLADYS",
        "client_second_name": "ELENA",
        "client_first_lastname": "VILLA",
        "client_second_lastname": "NARANJO",
        "client_birth_date": "1987-06-21",
        "client_gender": "F",
        "client_city": "Envigado",
        "client_department": "Antioquia",
        "vehicle_plate": "MGV239",
        "vehicle_model_year": "2013",
        "vehicle_brand": "VOLKSWAGEN",
        "vehicle_reference": "Jetta",
        "vehicle_full_reference": "VOLKSWAGEN jetta",
        "vehicle_state": "Usado",
        "manual_cf_code": "",
        "manual_ch_code": "",
        "policy_number": "900001250624",
        "policy_number_allianz": "23486665"
      },
      "updated_at": "2025-08-21T12:19:34.656498"
    },
    {
      "id": "20250818_103000",
      "name": "SERGIO AREIZA",
      "created_at": "2025-08-18T10:30:00.000000",
      "data": {
        "client_document_number": "71750823",
        "client_first_name": "SERGIO",
        "client_second_name": "ALEXIS",
        "client_first_lastname": "AREIZA",
        "client_second_lastname": "LOAIZA",
        "client_birth_date": "1974-07-06",
        "client_gender": "M",
        "client_city": "MEDELLIN",
        "client_department": "ANTIOQUIA",
        "vehicle_plate": "GEN294",
        "vehicle_model_year": "2026",
        "vehicle_brand": "Mazda",
        "vehicle_reference": "Cx50 - utilitario deportivo 4x4",
        "vehicle_full_reference": "MAZDA CX-50 GRAND TOURING",
        "vehicle_state": "Nuevo",
        "manual_cf_code": "20900024001",
        "manual_ch_code": "20900024001",
        "policy_number": "040007325677",
        "policy_number_allianz": "23541048"
      },
      "updated_at": "2025-08-21T12:19:43.776732"
    }
  ]
}